<?xml version="1.0" encoding="UTF-8"?>
<!--Generated by python, Author: Mengze.-->
<osm>
    <node id="10001" lat="39.95788916" lon="116.31553637">
        <tag k="highway" v="traffic_signals"/>
    </node>
    <node id="10002" lat="39.95833513" lon="116.31642130"/>
    <node id="10003" lat="39.95832456" lon="116.31633449"/>
    <node id="10004" lat="39.95833413" lon="116.31622731"/>
    <node id="10005" lat="39.95836603" lon="116.31607524"/>
    <node id="10006" lat="39.95837296" lon="116.31599768"/>
    <node id="10007" lat="39.95838468" lon="116.31586642"/>
    <node id="10008" lat="39.95833357" lon="116.31575801"/>
    <node id="10009" lat="39.95824162" lon="116.31571773"/>
    <node id="10010" lat="39.95816625" lon="116.31570925"/>
    <node id="10011" lat="39.95809063" lon="116.31571819"/>
    <node id="10012" lat="39.95801733" lon="116.31571556"/>
    <node id="10013" lat="39.95796766" lon="116.31570983"/>
    <node id="10014" lat="39.95789052" lon="116.31558744"/>
    <node id="10015" lat="39.95789749" lon="116.31563354"/>
    <node id="10016" lat="39.95788425" lon="116.31546250"/>
    <node id="10017" lat="39.95788020" lon="116.31531025"/>
    <node id="10018" lat="39.95788509" lon="116.31538369"/>
    <node id="10019" lat="39.95785904" lon="116.31517460"/>
    <node id="10020" lat="39.95788017" lon="116.31524294"/>
    <node id="10021" lat="39.95784547" lon="116.31507928"/>
    <node id="10022" lat="39.95785596" lon="116.31495727"/>
    <node id="10023" lat="39.95785628" lon="116.31485122"/>
    <node id="10024" lat="39.95785615" lon="116.31470603"/>
    <node id="10025" lat="39.95785345" lon="116.31463356"/>
    <node id="10026" lat="39.95784701" lon="116.31445003"/>
    <node id="10027" lat="39.95784745" lon="116.31449450"/>
    <node id="10028" lat="39.95784432" lon="116.31437791"/>
    <node id="10029" lat="39.95783243" lon="116.31429000"/>
    <node id="10030" lat="39.95780897" lon="116.31420382"/>
    <node id="10031" lat="39.95780984" lon="116.31407833"/>
    <node id="10032" lat="39.95781621" lon="116.31400701"/>
    <node id="10033" lat="39.95779586" lon="116.31388954"/>
    <node id="10034" lat="39.95775882" lon="116.31379106"/>
    <node id="10035" lat="39.95775222" lon="116.31369519"/>
    <node id="10036" lat="39.95775267" lon="116.31357730"/>
    <node id="10037" lat="39.95772992" lon="116.31349527"/>
    <node id="10038" lat="39.95773545" lon="116.31337737"/>
    <node id="10039" lat="39.95773665" lon="116.31330813"/>
    <node id="10040" lat="39.95768087" lon="116.31332316"/>
    <node id="10041" lat="39.95761583" lon="116.31328746"/>
    <node id="10042" lat="39.95755250" lon="116.31329887"/>
    <node id="10043" lat="39.95747404" lon="116.31333353"/>
    <node id="10044" lat="39.95738870" lon="116.31335884"/>
    <node id="10045" lat="39.95731244" lon="116.31335217"/>
    <node id="10046" lat="39.95724305" lon="116.31333469"/>
    <node id="10047" lat="39.95716743" lon="116.31335344"/>
    <node id="10048" lat="39.95710947" lon="116.31342766"/>
    <node id="10049" lat="39.95705195" lon="116.31346156"/>
    <node id="10050" lat="39.95697846" lon="116.31350217"/>
    <node id="10051" lat="39.95692460" lon="116.31351544"/>
    <node id="10052" lat="39.95686022" lon="116.31347374"/>
    <node id="10053" lat="39.95681441" lon="116.31341115"/>
    <node id="10054" lat="39.95679120" lon="116.31328339"/>
    <node id="10055" lat="39.95675555" lon="116.31317426"/>
    <node id="10056" lat="39.95676420" lon="116.31307242"/>
    <node id="10057" lat="39.95677558" lon="116.31294491"/>
    <node id="10058" lat="39.95678480" lon="116.31282342"/>
    <node id="10059" lat="39.95679244" lon="116.31272237"/>
    <node id="10060" lat="39.95680007" lon="116.31262148"/>
    <node id="10061" lat="39.95673276" lon="116.31257929"/>
    <node id="10062" lat="39.95667662" lon="116.31257686"/>
    <node id="10063" lat="39.95659244" lon="116.31256604"/>
    <node id="10064" lat="39.95651894" lon="116.31256373"/>
    <node id="10065" lat="39.95642660" lon="116.31256690"/>
    <node id="10066" lat="39.95635657" lon="116.31255983"/>
    <node id="10067" lat="39.95626761" lon="116.31256767"/>
    <node id="10068" lat="39.95620499" lon="116.31259337"/>
    <node id="10069" lat="39.95616069" lon="116.31266975"/>
    <node id="10070" lat="39.95613953" lon="116.31278217"/>
    <node id="10071" lat="39.95612998" lon="116.31288959"/>
    <node id="10072" lat="39.95611910" lon="116.31301547"/>
    <node id="10073" lat="39.95609481" lon="116.31316893"/>
    <node id="10074" lat="39.95612544" lon="116.31328784"/>
    <node id="10075" lat="39.95613920" lon="116.31338799"/>
    <node id="10076" lat="39.95613037" lon="116.31348693"/>
    <node id="10077" lat="39.95612488" lon="116.31359094"/>
    <node id="10078" lat="39.95612529" lon="116.31371011"/>
    <node id="10079" lat="39.95611334" lon="116.31383753"/>
    <node id="10080" lat="39.95611461" lon="116.31395723"/>
    <node id="10081" lat="39.95613888" lon="116.31407643"/>
    <node id="10082" lat="39.95613446" lon="116.31422066"/>
    <node id="10083" lat="39.95613316" lon="116.31437081"/>
    <node id="10084" lat="39.95614535" lon="116.31445126"/>
    <node id="10085" lat="39.95616141" lon="116.31457708"/>
    <node id="10086" lat="39.95618785" lon="116.31467681"/>
    <node id="10087" lat="39.95622099" lon="116.31474938"/>
    <node id="10088" lat="39.95629960" lon="116.31476937"/>
    <node id="10089" lat="39.95641835" lon="116.31477920"/>
    <node id="10090" lat="39.95650101" lon="116.31475371"/>
    <node id="10091" lat="39.95656564" lon="116.31475404"/>
    <node id="10092" lat="39.95660513" lon="116.31475328">
        <tag k="highway" v="traffic_signals"/>
    </node>
    <way id="10000">
        <nd ref="10001"/>
        <nd ref="10002"/>
        <nd ref="10003"/>
        <nd ref="10004"/>
        <nd ref="10005"/>
        <nd ref="10006"/>
        <nd ref="10007"/>
        <nd ref="10008"/>
        <nd ref="10009"/>
        <nd ref="10010"/>
        <nd ref="10011"/>
        <nd ref="10012"/>
        <nd ref="10013"/>
        <nd ref="10014"/>
        <nd ref="10015"/>
        <nd ref="10016"/>
        <nd ref="10017"/>
        <nd ref="10018"/>
        <nd ref="10019"/>
        <nd ref="10020"/>
        <nd ref="10021"/>
        <nd ref="10022"/>
        <nd ref="10023"/>
        <nd ref="10024"/>
        <nd ref="10025"/>
        <nd ref="10026"/>
        <nd ref="10027"/>
        <nd ref="10028"/>
        <nd ref="10029"/>
        <nd ref="10030"/>
        <nd ref="10031"/>
        <nd ref="10032"/>
        <nd ref="10033"/>
        <nd ref="10034"/>
        <nd ref="10035"/>
        <nd ref="10036"/>
        <nd ref="10037"/>
        <nd ref="10038"/>
        <nd ref="10039"/>
        <nd ref="10040"/>
        <nd ref="10041"/>
        <nd ref="10042"/>
        <nd ref="10043"/>
        <nd ref="10044"/>
        <nd ref="10045"/>
        <nd ref="10046"/>
        <nd ref="10047"/>
        <nd ref="10048"/>
        <nd ref="10049"/>
        <nd ref="10050"/>
        <nd ref="10051"/>
        <nd ref="10052"/>
        <nd ref="10053"/>
        <nd ref="10054"/>
        <nd ref="10055"/>
        <nd ref="10056"/>
        <nd ref="10057"/>
        <nd ref="10058"/>
        <nd ref="10059"/>
        <nd ref="10060"/>
        <nd ref="10061"/>
        <nd ref="10062"/>
        <nd ref="10063"/>
        <nd ref="10064"/>
        <nd ref="10065"/>
        <nd ref="10066"/>
        <nd ref="10067"/>
        <nd ref="10068"/>
        <nd ref="10069"/>
        <nd ref="10070"/>
        <nd ref="10071"/>
        <nd ref="10072"/>
        <nd ref="10073"/>
        <nd ref="10074"/>
        <nd ref="10075"/>
        <nd ref="10076"/>
        <nd ref="10077"/>
        <nd ref="10078"/>
        <nd ref="10079"/>
        <nd ref="10080"/>
        <nd ref="10081"/>
        <nd ref="10082"/>
        <nd ref="10083"/>
        <nd ref="10084"/>
        <nd ref="10085"/>
        <nd ref="10086"/>
        <nd ref="10087"/>
        <nd ref="10088"/>
        <nd ref="10089"/>
        <nd ref="10090"/>
        <nd ref="10091"/>
        <nd ref="10092"/>
        <tag k="name:en" v="double way"/>
    </way>
</osm>
